{"index":{"links":{"/":[{"source":"/","target":"/%E6%95%B0%E5%AD%97%E8%8A%B1%E5%9B%AD","text":"数字花园"}],"/frontend/deploy":[{"source":"/frontend/deploy","target":"/_index","text":"_index"}]},"backlinks":{"/%E6%95%B0%E5%AD%97%E8%8A%B1%E5%9B%AD":[{"source":"/","target":"/%E6%95%B0%E5%AD%97%E8%8A%B1%E5%9B%AD","text":"数字花园"}],"/_index":[{"source":"/frontend/deploy","target":"/_index","text":"_index"}]}},"links":[{"source":"/","target":"/%E6%95%B0%E5%AD%97%E8%8A%B1%E5%9B%AD","text":"数字花园"},{"source":"/frontend/deploy","target":"/_index","text":"_index"}]}